aws_vault_migrate/__init__.py
aws_vault_migrate/cli.py
aws_vault_migrate-0.2.2.dist-info/LICENSE
aws_vault_migrate-0.2.2.dist-info/METADATA
aws_vault_migrate-0.2.2.dist-info/WHEEL
aws_vault_migrate-0.2.2.dist-info/entry_points.txt
aws_vault_migrate-0.2.2.dist-info/top_level.txt
aws_vault_migrate-0.2.2.dist-info/RECORD
